windscribe/__init__.py
windscribe/windscribe.py
python_windscribe-2020.9.16.dist-info/LICENSE
python_windscribe-2020.9.16.dist-info/METADATA
python_windscribe-2020.9.16.dist-info/WHEEL
python_windscribe-2020.9.16.dist-info/top_level.txt
python_windscribe-2020.9.16.dist-info/RECORD
